devart/googlesheets/__init__.py
devart/googlesheets/googlesheets.cp313-win_amd64.pyd
devart/googlesheets/googlesheets.pyi
devart/googlesheets/GoogleSheets/Devart.Python.GoogleSheetsEngine.dll
devart/googlesheets/GoogleSheets/sqlite3.dll
devart/googlesheets/sqlalchemy/__init__.py
devart_googlesheets_connector-1.0.1.dist-info/LICENSE
devart_googlesheets_connector-1.0.1.dist-info/METADATA
devart_googlesheets_connector-1.0.1.dist-info/WHEEL
devart_googlesheets_connector-1.0.1.dist-info/top_level.txt
devart_googlesheets_connector-1.0.1.dist-info/RECORD
